<model>
	<voxels>
		<voxel x="-8" y="-3" z="1" r="0.3255" g="0.3255" b="0.3255" a="1.0" />
		<voxel x="-7" y="-3" z="1" r="0.3255" g="0.3255" b="0.3255" a="1.0" />
		<voxel x="-8" y="-3" z="0" r="0.3255" g="0.3255" b="0.3255" a="1.0" />
		<voxel x="-7" y="-3" z="0" r="0.3255" g="0.3255" b="0.3255" a="1.0" />
		<voxel x="-8" y="-3" z="-1" r="0.3255" g="0.3255" b="0.3255" a="1.0" />
		<voxel x="-7" y="-3" z="-1" r="0.3255" g="0.3255" b="0.3255" a="1.0" />
		<voxel x="-8" y="-2" z="2" r="0.3255" g="0.3255" b="0.3255" a="1.0" />
		<voxel x="-7" y="-2" z="2" r="0.3255" g="0.3255" b="0.3255" a="1.0" />
		<voxel x="-9" y="-2" z="1" r="0.3255" g="0.3255" b="0.3255" a="1.0" />
		<voxel x="-8" y="-2" z="1" r="0.3255" g="0.3255" b="0.3255" a="1.0" />
		<voxel x="-7" y="-2" z="1" r="0.3255" g="0.3255" b="0.3255" a="1.0" />
		<voxel x="-6" y="-2" z="1" r="0.3255" g="0.3255" b="0.3255" a="1.0" />
		<voxel x="-9" y="-2" z="0" r="0.3255" g="0.3255" b="0.3255" a="1.0" />
		<voxel x="-8" y="-2" z="0" r="0.3255" g="0.3255" b="0.3255" a="1.0" />
		<voxel x="-7" y="-2" z="0" r="0.3255" g="0.3255" b="0.3255" a="1.0" />
		<voxel x="-6" y="-2" z="0" r="0.3255" g="0.3255" b="0.3255" a="1.0" />
		<voxel x="-1" y="-2" z="0" r="0.3255" g="0.3255" b="0.3255" a="1.0" />
		<voxel x="0" y="-2" z="0" r="0.3255" g="0.3255" b="0.3255" a="1.0" />
		<voxel x="-9" y="-2" z="-1" r="0.3255" g="0.3255" b="0.3255" a="1.0" />
		<voxel x="-8" y="-2" z="-1" r="0.3255" g="0.3255" b="0.3255" a="1.0" />
		<voxel x="-7" y="-2" z="-1" r="0.3255" g="0.3255" b="0.3255" a="1.0" />
		<voxel x="-6" y="-2" z="-1" r="0.3255" g="0.3255" b="0.3255" a="1.0" />
		<voxel x="-8" y="-2" z="-2" r="0.3255" g="0.3255" b="0.3255" a="1.0" />
		<voxel x="-7" y="-2" z="-2" r="0.3255" g="0.3255" b="0.3255" a="1.0" />
		<voxel x="-8" y="-1" z="3" r="0.3255" g="0.3255" b="0.3255" a="1.0" />
		<voxel x="-7" y="-1" z="3" r="0.3255" g="0.3255" b="0.3255" a="1.0" />
		<voxel x="-9" y="-1" z="2" r="0.3255" g="0.3255" b="0.3255" a="1.0" />
		<voxel x="-8" y="-1" z="2" r="0.3255" g="0.3255" b="0.3255" a="1.0" />
		<voxel x="-7" y="-1" z="2" r="0.3255" g="0.3255" b="0.3255" a="1.0" />
		<voxel x="-6" y="-1" z="2" r="0.3255" g="0.3255" b="0.3255" a="1.0" />
		<voxel x="-9" y="-1" z="1" r="0.3255" g="0.3255" b="0.3255" a="1.0" />
		<voxel x="-8" y="-1" z="1" r="0.3255" g="0.3255" b="0.3255" a="1.0" />
		<voxel x="-7" y="-1" z="1" r="0.3255" g="0.3255" b="0.3255" a="1.0" />
		<voxel x="-9" y="-1" z="0" r="0.3255" g="0.3255" b="0.3255" a="1.0" />
		<voxel x="-8" y="-1" z="0" r="0.3255" g="0.3255" b="0.3255" a="1.0" />
		<voxel x="-7" y="-1" z="0" r="0.3255" g="0.3255" b="0.3255" a="1.0" />
		<voxel x="-6" y="-1" z="0" r="0.3255" g="0.3255" b="0.3255" a="1.0" />
		<voxel x="-2" y="-1" z="0" r="0.4353" g="0.4353" b="0.4353" a="1.0" />
		<voxel x="-1" y="-1" z="0" r="0.3804" g="0.3804" b="0.3804" a="1.0" />
		<voxel x="-9" y="-1" z="-1" r="0.3255" g="0.3255" b="0.3255" a="1.0" />
		<voxel x="-8" y="-1" z="-1" r="0.3255" g="0.3255" b="0.3255" a="1.0" />
		<voxel x="-7" y="-1" z="-1" r="0.3255" g="0.3255" b="0.3255" a="1.0" />
		<voxel x="-9" y="-1" z="-2" r="0.3255" g="0.3255" b="0.3255" a="1.0" />
		<voxel x="-8" y="-1" z="-2" r="0.3255" g="0.3255" b="0.3255" a="1.0" />
		<voxel x="-7" y="-1" z="-2" r="0.3255" g="0.3255" b="0.3255" a="1.0" />
		<voxel x="-6" y="-1" z="-2" r="0.3255" g="0.3255" b="0.3255" a="1.0" />
		<voxel x="-8" y="-1" z="-3" r="0.3255" g="0.3255" b="0.3255" a="1.0" />
		<voxel x="-7" y="-1" z="-3" r="0.3255" g="0.3255" b="0.3255" a="1.0" />
		<voxel x="-8" y="0" z="3" r="0.3255" g="0.3255" b="0.3255" a="1.0" />
		<voxel x="-7" y="0" z="3" r="0.3255" g="0.3255" b="0.3255" a="1.0" />
		<voxel x="-9" y="0" z="2" r="0.3255" g="0.3255" b="0.3255" a="1.0" />
		<voxel x="-8" y="0" z="2" r="0.3255" g="0.3255" b="0.3255" a="1.0" />
		<voxel x="-7" y="0" z="2" r="0.3255" g="0.3255" b="0.3255" a="1.0" />
		<voxel x="-6" y="0" z="2" r="0.3255" g="0.3255" b="0.3255" a="1.0" />
		<voxel x="-9" y="0" z="1" r="0.3255" g="0.3255" b="0.3255" a="1.0" />
		<voxel x="-8" y="0" z="1" r="0.3255" g="0.3255" b="0.3255" a="1.0" />
		<voxel x="-7" y="0" z="1" r="0.3255" g="0.3255" b="0.3255" a="1.0" />
		<voxel x="-6" y="0" z="1" r="0.3255" g="0.3255" b="0.3255" a="1.0" />
		<voxel x="-8" y="0" z="0" r="0.3255" g="0.3255" b="0.3255" a="1.0" />
		<voxel x="-7" y="0" z="0" r="0.3255" g="0.3255" b="0.3255" a="1.0" />
		<voxel x="-6" y="0" z="0" r="0.3255" g="0.3255" b="0.3255" a="1.0" />
		<voxel x="-2" y="0" z="0" r="0.549" g="0.549" b="0.549" a="1.0" />
		<voxel x="-1" y="0" z="0" r="0.4353" g="0.4353" b="0.4353" a="1.0" />
		<voxel x="-9" y="0" z="-1" r="0.3255" g="0.3255" b="0.3255" a="1.0" />
		<voxel x="-8" y="0" z="-1" r="0.3255" g="0.3255" b="0.3255" a="1.0" />
		<voxel x="-7" y="0" z="-1" r="0.3255" g="0.3255" b="0.3255" a="1.0" />
		<voxel x="-6" y="0" z="-1" r="0.3255" g="0.3255" b="0.3255" a="1.0" />
		<voxel x="-9" y="0" z="-2" r="0.3255" g="0.3255" b="0.3255" a="1.0" />
		<voxel x="-8" y="0" z="-2" r="0.3255" g="0.3255" b="0.3255" a="1.0" />
		<voxel x="-7" y="0" z="-2" r="0.3255" g="0.3255" b="0.3255" a="1.0" />
		<voxel x="-6" y="0" z="-2" r="0.3255" g="0.3255" b="0.3255" a="1.0" />
		<voxel x="-8" y="0" z="-3" r="0.3255" g="0.3255" b="0.3255" a="1.0" />
		<voxel x="-7" y="0" z="-3" r="0.3255" g="0.3255" b="0.3255" a="1.0" />
		<voxel x="-8" y="1" z="3" r="0.3255" g="0.3255" b="0.3255" a="1.0" />
		<voxel x="-7" y="1" z="3" r="0.3255" g="0.3255" b="0.3255" a="1.0" />
		<voxel x="-9" y="1" z="2" r="0.3255" g="0.3255" b="0.3255" a="1.0" />
		<voxel x="-8" y="1" z="2" r="0.3255" g="0.3255" b="0.3255" a="1.0" />
		<voxel x="-7" y="1" z="2" r="0.3255" g="0.3255" b="0.3255" a="1.0" />
		<voxel x="-6" y="1" z="2" r="0.3255" g="0.3255" b="0.3255" a="1.0" />
		<voxel x="-9" y="1" z="1" r="0.3255" g="0.3255" b="0.3255" a="1.0" />
		<voxel x="-8" y="1" z="1" r="0.3255" g="0.3255" b="0.3255" a="1.0" />
		<voxel x="-7" y="1" z="1" r="0.3255" g="0.3255" b="0.3255" a="1.0" />
		<voxel x="-9" y="1" z="0" r="0.3255" g="0.3255" b="0.3255" a="1.0" />
		<voxel x="-8" y="1" z="0" r="0.3255" g="0.3255" b="0.3255" a="1.0" />
		<voxel x="-7" y="1" z="0" r="0.3255" g="0.3255" b="0.3255" a="1.0" />
		<voxel x="-6" y="1" z="0" r="0.3255" g="0.3255" b="0.3255" a="1.0" />
		<voxel x="-3" y="1" z="0" r="0.6039" g="0.6039" b="0.6039" a="1.0" />
		<voxel x="-2" y="1" z="0" r="0.6039" g="0.6039" b="0.6039" a="1.0" />
		<voxel x="-1" y="1" z="0" r="0.549" g="0.549" b="0.549" a="1.0" />
		<voxel x="-9" y="1" z="-1" r="0.3255" g="0.3255" b="0.3255" a="1.0" />
		<voxel x="-8" y="1" z="-1" r="0.3255" g="0.3255" b="0.3255" a="1.0" />
		<voxel x="-7" y="1" z="-1" r="0.3255" g="0.3255" b="0.3255" a="1.0" />
		<voxel x="-9" y="1" z="-2" r="0.3255" g="0.3255" b="0.3255" a="1.0" />
		<voxel x="-8" y="1" z="-2" r="0.3255" g="0.3255" b="0.3255" a="1.0" />
		<voxel x="-7" y="1" z="-2" r="0.3255" g="0.3255" b="0.3255" a="1.0" />
		<voxel x="-6" y="1" z="-2" r="0.3255" g="0.3255" b="0.3255" a="1.0" />
		<voxel x="-8" y="1" z="-3" r="0.3255" g="0.3255" b="0.3255" a="1.0" />
		<voxel x="-7" y="1" z="-3" r="0.3255" g="0.3255" b="0.3255" a="1.0" />
		<voxel x="-8" y="2" z="2" r="0.3255" g="0.3255" b="0.3255" a="1.0" />
		<voxel x="-7" y="2" z="2" r="0.3255" g="0.3255" b="0.3255" a="1.0" />
		<voxel x="-9" y="2" z="1" r="0.3255" g="0.3255" b="0.3255" a="1.0" />
		<voxel x="-7" y="2" z="1" r="0.3255" g="0.3255" b="0.3255" a="1.0" />
		<voxel x="-6" y="2" z="1" r="0.3255" g="0.3255" b="0.3255" a="1.0" />
		<voxel x="-16" y="2" z="0" r="0.4902" g="0.4902" b="0.4902" a="1.0" />
		<voxel x="-15" y="2" z="0" r="0.4353" g="0.4353" b="0.4353" a="1.0" />
		<voxel x="-14" y="2" z="0" r="0.3804" g="0.3804" b="0.3804" a="1.0" />
		<voxel x="-13" y="2" z="0" r="0.3569" g="0.3569" b="0.3569" a="1.0" />
		<voxel x="-9" y="2" z="0" r="0.3255" g="0.3255" b="0.3255" a="1.0" />
		<voxel x="-7" y="2" z="0" r="0.3255" g="0.3255" b="0.3255" a="1.0" />
		<voxel x="-6" y="2" z="0" r="0.3255" g="0.3255" b="0.3255" a="1.0" />
		<voxel x="-4" y="2" z="0" r="0.6039" g="0.6039" b="0.6039" a="1.0" />
		<voxel x="-3" y="2" z="0" r="0.6039" g="0.6039" b="0.6039" a="1.0" />
		<voxel x="-2" y="2" z="0" r="0.6039" g="0.6039" b="0.6039" a="1.0" />
		<voxel x="-9" y="2" z="-1" r="0.3255" g="0.3255" b="0.3255" a="1.0" />
		<voxel x="-8" y="2" z="-1" r="0.3255" g="0.3255" b="0.3255" a="1.0" />
		<voxel x="-7" y="2" z="-1" r="0.3255" g="0.3255" b="0.3255" a="1.0" />
		<voxel x="-6" y="2" z="-1" r="0.3255" g="0.3255" b="0.3255" a="1.0" />
		<voxel x="-8" y="2" z="-2" r="0.3255" g="0.3255" b="0.3255" a="1.0" />
		<voxel x="-7" y="2" z="-2" r="0.3255" g="0.3255" b="0.3255" a="1.0" />
		<voxel x="-16" y="3" z="1" r="0.549" g="0.549" b="0.549" a="1.0" />
		<voxel x="-15" y="3" z="1" r="0.4902" g="0.4902" b="0.4902" a="1.0" />
		<voxel x="-14" y="3" z="1" r="0.3804" g="0.3804" b="0.3804" a="1.0" />
		<voxel x="-13" y="3" z="1" r="0.3569" g="0.3569" b="0.3569" a="1.0" />
		<voxel x="-12" y="3" z="1" r="0.3569" g="0.3569" b="0.3569" a="1.0" />
		<voxel x="-11" y="3" z="1" r="0.3569" g="0.3569" b="0.3569" a="1.0" />
		<voxel x="-10" y="3" z="1" r="0.3569" g="0.3569" b="0.3569" a="1.0" />
		<voxel x="-8" y="3" z="1" r="0.3255" g="0.3255" b="0.3255" a="1.0" />
		<voxel x="-7" y="3" z="1" r="0.3255" g="0.3255" b="0.3255" a="1.0" />
		<voxel x="1" y="3" z="1" r="0.6039" g="0.6039" b="0.6039" a="1.0" />
		<voxel x="2" y="3" z="1" r="0.549" g="0.549" b="0.549" a="1.0" />
		<voxel x="3" y="3" z="1" r="0.4902" g="0.4902" b="0.4902" a="1.0" />
		<voxel x="4" y="3" z="1" r="0.4353" g="0.4353" b="0.4353" a="1.0" />
		<voxel x="5" y="3" z="1" r="0.3804" g="0.3804" b="0.3804" a="1.0" />
		<voxel x="6" y="3" z="1" r="0.3255" g="0.3255" b="0.3255" a="1.0" />
		<voxel x="7" y="3" z="1" r="0.2667" g="0.2667" b="0.2667" a="1.0" />
		<voxel x="8" y="3" z="1" r="0.2118" g="0.2118" b="0.2118" a="1.0" />
		<voxel x="-16" y="3" z="0" r="0.3569" g="0.3569" b="0.3569" a="1.0" />
		<voxel x="-15" y="3" z="0" r="0.3569" g="0.3569" b="0.3569" a="1.0" />
		<voxel x="-14" y="3" z="0" r="0.3569" g="0.3569" b="0.3569" a="1.0" />
		<voxel x="-13" y="3" z="0" r="0.3569" g="0.3569" b="0.3569" a="1.0" />
		<voxel x="-12" y="3" z="0" r="0.3569" g="0.3569" b="0.3569" a="1.0" />
		<voxel x="-11" y="3" z="0" r="0.3569" g="0.3569" b="0.3569" a="1.0" />
		<voxel x="-10" y="3" z="0" r="0.3569" g="0.3569" b="0.3569" a="1.0" />
		<voxel x="-8" y="3" z="0" r="0.3255" g="0.3255" b="0.3255" a="1.0" />
		<voxel x="-7" y="3" z="0" r="0.3255" g="0.3255" b="0.3255" a="1.0" />
		<voxel x="-4" y="3" z="0" r="0.6039" g="0.6039" b="0.6039" a="1.0" />
		<voxel x="-2" y="3" z="0" r="0.6039" g="0.6039" b="0.6039" a="1.0" />
		<voxel x="0" y="3" z="0" r="0.6039" g="0.6039" b="0.6039" a="1.0" />
		<voxel x="1" y="3" z="0" r="0.549" g="0.549" b="0.549" a="1.0" />
		<voxel x="2" y="3" z="0" r="0.4902" g="0.4902" b="0.4902" a="1.0" />
		<voxel x="3" y="3" z="0" r="0.4353" g="0.4353" b="0.4353" a="1.0" />
		<voxel x="4" y="3" z="0" r="0.3804" g="0.3804" b="0.3804" a="1.0" />
		<voxel x="5" y="3" z="0" r="0.3255" g="0.3255" b="0.3255" a="1.0" />
		<voxel x="6" y="3" z="0" r="0.2667" g="0.2667" b="0.2667" a="1.0" />
		<voxel x="7" y="3" z="0" r="0.2118" g="0.2118" b="0.2118" a="1.0" />
		<voxel x="8" y="3" z="0" r="0.2118" g="0.2118" b="0.2118" a="1.0" />
		<voxel x="-16" y="3" z="-1" r="0.549" g="0.549" b="0.549" a="1.0" />
		<voxel x="-15" y="3" z="-1" r="0.4902" g="0.4902" b="0.4902" a="1.0" />
		<voxel x="-14" y="3" z="-1" r="0.4353" g="0.4353" b="0.4353" a="1.0" />
		<voxel x="-13" y="3" z="-1" r="0.3804" g="0.3804" b="0.3804" a="1.0" />
		<voxel x="-12" y="3" z="-1" r="0.3804" g="0.3804" b="0.3804" a="1.0" />
		<voxel x="-11" y="3" z="-1" r="0.3569" g="0.3569" b="0.3569" a="1.0" />
		<voxel x="-10" y="3" z="-1" r="0.3569" g="0.3569" b="0.3569" a="1.0" />
		<voxel x="-8" y="3" z="-1" r="0.3255" g="0.3255" b="0.3255" a="1.0" />
		<voxel x="-7" y="3" z="-1" r="0.3255" g="0.3255" b="0.3255" a="1.0" />
		<voxel x="1" y="3" z="-1" r="0.6039" g="0.6039" b="0.6039" a="1.0" />
		<voxel x="2" y="3" z="-1" r="0.549" g="0.549" b="0.549" a="1.0" />
		<voxel x="3" y="3" z="-1" r="0.4902" g="0.4902" b="0.4902" a="1.0" />
		<voxel x="4" y="3" z="-1" r="0.4353" g="0.4353" b="0.4353" a="1.0" />
		<voxel x="5" y="3" z="-1" r="0.3804" g="0.3804" b="0.3804" a="1.0" />
		<voxel x="6" y="3" z="-1" r="0.3255" g="0.3255" b="0.3255" a="1.0" />
		<voxel x="7" y="3" z="-1" r="0.2667" g="0.2667" b="0.2667" a="1.0" />
		<voxel x="8" y="3" z="-1" r="0.2118" g="0.2118" b="0.2118" a="1.0" />
		<voxel x="-18" y="4" z="1" r="0.3569" g="0.3569" b="0.3569" a="1.0" />
		<voxel x="-17" y="4" z="1" r="0.3569" g="0.3569" b="0.3569" a="1.0" />
		<voxel x="-16" y="4" z="1" r="0.3569" g="0.3569" b="0.3569" a="1.0" />
		<voxel x="-15" y="4" z="1" r="1.0" g="0.7608" b="0.0" a="1.0" />
		<voxel x="-14" y="4" z="1" r="1.0" g="0.7608" b="0.0" a="1.0" />
		<voxel x="-13" y="4" z="1" r="1.0" g="0.7608" b="0.0" a="1.0" />
		<voxel x="-12" y="4" z="1" r="0.3569" g="0.3569" b="0.3569" a="1.0" />
		<voxel x="-11" y="4" z="1" r="0.3569" g="0.3569" b="0.3569" a="1.0" />
		<voxel x="-10" y="4" z="1" r="0.3373" g="0.3373" b="0.3373" a="1.0" />
		<voxel x="-9" y="4" z="1" r="0.6039" g="0.6039" b="0.6039" a="1.0" />
		<voxel x="-8" y="4" z="1" r="0.6039" g="0.6039" b="0.6039" a="1.0" />
		<voxel x="-7" y="4" z="1" r="0.549" g="0.549" b="0.549" a="1.0" />
		<voxel x="-6" y="4" z="1" r="0.6039" g="0.6039" b="0.6039" a="1.0" />
		<voxel x="-5" y="4" z="1" r="0.549" g="0.549" b="0.549" a="1.0" />
		<voxel x="-4" y="4" z="1" r="0.6039" g="0.6039" b="0.6039" a="1.0" />
		<voxel x="-3" y="4" z="1" r="0.6039" g="0.6039" b="0.6039" a="1.0" />
		<voxel x="-2" y="4" z="1" r="0.6039" g="0.6039" b="0.6039" a="1.0" />
		<voxel x="-1" y="4" z="1" r="0.6039" g="0.6039" b="0.6039" a="1.0" />
		<voxel x="0" y="4" z="1" r="0.6039" g="0.6039" b="0.6039" a="1.0" />
		<voxel x="1" y="4" z="1" r="0.549" g="0.549" b="0.549" a="1.0" />
		<voxel x="2" y="4" z="1" r="0.4902" g="0.4902" b="0.4902" a="1.0" />
		<voxel x="3" y="4" z="1" r="0.4353" g="0.4353" b="0.4353" a="1.0" />
		<voxel x="4" y="4" z="1" r="0.3804" g="0.3804" b="0.3804" a="1.0" />
		<voxel x="5" y="4" z="1" r="0.3255" g="0.3255" b="0.3255" a="1.0" />
		<voxel x="6" y="4" z="1" r="0.2667" g="0.2667" b="0.2667" a="1.0" />
		<voxel x="7" y="4" z="1" r="0.3255" g="0.3255" b="0.3255" a="1.0" />
		<voxel x="8" y="4" z="1" r="0.2118" g="0.2118" b="0.2118" a="1.0" />
		<voxel x="-19" y="4" z="0" r="0.7059" g="0.7059" b="0.7059" a="1.0" />
		<voxel x="-18" y="4" z="0" r="0.3569" g="0.3569" b="0.3569" a="1.0" />
		<voxel x="-17" y="4" z="0" r="0.3569" g="0.3569" b="0.3569" a="1.0" />
		<voxel x="-16" y="4" z="0" r="0.3569" g="0.3569" b="0.3569" a="1.0" />
		<voxel x="-15" y="4" z="0" r="0.3569" g="0.3569" b="0.3569" a="1.0" />
		<voxel x="-14" y="4" z="0" r="0.3569" g="0.3569" b="0.3569" a="1.0" />
		<voxel x="-13" y="4" z="0" r="0.3569" g="0.3569" b="0.3569" a="1.0" />
		<voxel x="-12" y="4" z="0" r="0.3569" g="0.3569" b="0.3569" a="1.0" />
		<voxel x="-11" y="4" z="0" r="0.3569" g="0.3569" b="0.3569" a="1.0" />
		<voxel x="-10" y="4" z="0" r="0.3059" g="0.3059" b="0.3059" a="1.0" />
		<voxel x="-9" y="4" z="0" r="0.6039" g="0.6039" b="0.6039" a="1.0" />
		<voxel x="-8" y="4" z="0" r="0.6039" g="0.6039" b="0.6039" a="1.0" />
		<voxel x="-7" y="4" z="0" r="0.6039" g="0.6039" b="0.6039" a="1.0" />
		<voxel x="-6" y="4" z="0" r="0.6039" g="0.6039" b="0.6039" a="1.0" />
		<voxel x="-5" y="4" z="0" r="0.6039" g="0.6039" b="0.6039" a="1.0" />
		<voxel x="-4" y="4" z="0" r="0.6039" g="0.6039" b="0.6039" a="1.0" />
		<voxel x="-3" y="4" z="0" r="0.6039" g="0.6039" b="0.6039" a="1.0" />
		<voxel x="-2" y="4" z="0" r="0.6039" g="0.6039" b="0.6039" a="1.0" />
		<voxel x="-1" y="4" z="0" r="0.4902" g="0.4902" b="0.4902" a="1.0" />
		<voxel x="0" y="4" z="0" r="0.549" g="0.549" b="0.549" a="1.0" />
		<voxel x="1" y="4" z="0" r="0.6039" g="0.6039" b="0.6039" a="1.0" />
		<voxel x="2" y="4" z="0" r="0.549" g="0.549" b="0.549" a="1.0" />
		<voxel x="3" y="4" z="0" r="0.4902" g="0.4902" b="0.4902" a="1.0" />
		<voxel x="4" y="4" z="0" r="0.4353" g="0.4353" b="0.4353" a="1.0" />
		<voxel x="5" y="4" z="0" r="0.3804" g="0.3804" b="0.3804" a="1.0" />
		<voxel x="6" y="4" z="0" r="0.3255" g="0.3255" b="0.3255" a="1.0" />
		<voxel x="7" y="4" z="0" r="0.2667" g="0.2667" b="0.2667" a="1.0" />
		<voxel x="8" y="4" z="0" r="0.2118" g="0.2118" b="0.2118" a="1.0" />
		<voxel x="-18" y="4" z="-1" r="0.3569" g="0.3569" b="0.3569" a="1.0" />
		<voxel x="-17" y="4" z="-1" r="0.3373" g="0.3373" b="0.3373" a="1.0" />
		<voxel x="-16" y="4" z="-1" r="0.3373" g="0.3373" b="0.3373" a="1.0" />
		<voxel x="-15" y="4" z="-1" r="1.0" g="0.7608" b="0.0" a="1.0" />
		<voxel x="-14" y="4" z="-1" r="1.0" g="0.7608" b="0.0" a="1.0" />
		<voxel x="-13" y="4" z="-1" r="1.0" g="0.7608" b="0.0" a="1.0" />
		<voxel x="-12" y="4" z="-1" r="0.3255" g="0.3255" b="0.3255" a="1.0" />
		<voxel x="-11" y="4" z="-1" r="0.3451" g="0.3451" b="0.3451" a="1.0" />
		<voxel x="-10" y="4" z="-1" r="0.3373" g="0.3373" b="0.3373" a="1.0" />
		<voxel x="-9" y="4" z="-1" r="0.6039" g="0.6039" b="0.6039" a="1.0" />
		<voxel x="-8" y="4" z="-1" r="0.6039" g="0.6039" b="0.6039" a="1.0" />
		<voxel x="-7" y="4" z="-1" r="0.549" g="0.549" b="0.549" a="1.0" />
		<voxel x="-6" y="4" z="-1" r="0.6039" g="0.6039" b="0.6039" a="1.0" />
		<voxel x="-5" y="4" z="-1" r="0.549" g="0.549" b="0.549" a="1.0" />
		<voxel x="-4" y="4" z="-1" r="0.6039" g="0.6039" b="0.6039" a="1.0" />
		<voxel x="-3" y="4" z="-1" r="0.6039" g="0.6039" b="0.6039" a="1.0" />
		<voxel x="-2" y="4" z="-1" r="0.6039" g="0.6039" b="0.6039" a="1.0" />
		<voxel x="-1" y="4" z="-1" r="0.6039" g="0.6039" b="0.6039" a="1.0" />
		<voxel x="0" y="4" z="-1" r="0.6039" g="0.6039" b="0.6039" a="1.0" />
		<voxel x="1" y="4" z="-1" r="0.549" g="0.549" b="0.549" a="1.0" />
		<voxel x="2" y="4" z="-1" r="0.4902" g="0.4902" b="0.4902" a="1.0" />
		<voxel x="3" y="4" z="-1" r="0.4353" g="0.4353" b="0.4353" a="1.0" />
		<voxel x="4" y="4" z="-1" r="0.3804" g="0.3804" b="0.3804" a="1.0" />
		<voxel x="5" y="4" z="-1" r="0.3255" g="0.3255" b="0.3255" a="1.0" />
		<voxel x="6" y="4" z="-1" r="0.2667" g="0.2667" b="0.2667" a="1.0" />
		<voxel x="7" y="4" z="-1" r="0.3255" g="0.3255" b="0.3255" a="1.0" />
		<voxel x="8" y="4" z="-1" r="0.2118" g="0.2118" b="0.2118" a="1.0" />
		<voxel x="-18" y="5" z="1" r="0.6039" g="0.6039" b="0.6039" a="1.0" />
		<voxel x="-17" y="5" z="1" r="0.6039" g="0.6039" b="0.6039" a="1.0" />
		<voxel x="-16" y="5" z="1" r="0.6039" g="0.6039" b="0.6039" a="1.0" />
		<voxel x="-15" y="5" z="1" r="0.6039" g="0.6039" b="0.6039" a="1.0" />
		<voxel x="-14" y="5" z="1" r="0.6039" g="0.6039" b="0.6039" a="1.0" />
		<voxel x="-13" y="5" z="1" r="0.549" g="0.549" b="0.549" a="1.0" />
		<voxel x="-12" y="5" z="1" r="0.549" g="0.549" b="0.549" a="1.0" />
		<voxel x="-11" y="5" z="1" r="0.4353" g="0.4353" b="0.4353" a="1.0" />
		<voxel x="-10" y="5" z="1" r="0.6039" g="0.6039" b="0.6039" a="1.0" />
		<voxel x="-9" y="5" z="1" r="0.6039" g="0.6039" b="0.6039" a="1.0" />
		<voxel x="-8" y="5" z="1" r="0.549" g="0.549" b="0.549" a="1.0" />
		<voxel x="-7" y="5" z="1" r="0.6039" g="0.6039" b="0.6039" a="1.0" />
		<voxel x="-6" y="5" z="1" r="0.4353" g="0.4353" b="0.4353" a="1.0" />
		<voxel x="-5" y="5" z="1" r="0.6039" g="0.6039" b="0.6039" a="1.0" />
		<voxel x="-4" y="5" z="1" r="0.6039" g="0.6039" b="0.6039" a="1.0" />
		<voxel x="-3" y="5" z="1" r="0.6039" g="0.6039" b="0.6039" a="1.0" />
		<voxel x="-2" y="5" z="1" r="0.4902" g="0.4902" b="0.4902" a="1.0" />
		<voxel x="-1" y="5" z="1" r="0.4902" g="0.4902" b="0.4902" a="1.0" />
		<voxel x="0" y="5" z="1" r="0.549" g="0.549" b="0.549" a="1.0" />
		<voxel x="1" y="5" z="1" r="0.6039" g="0.6039" b="0.6039" a="1.0" />
		<voxel x="2" y="5" z="1" r="0.549" g="0.549" b="0.549" a="1.0" />
		<voxel x="3" y="5" z="1" r="0.4902" g="0.4902" b="0.4902" a="1.0" />
		<voxel x="4" y="5" z="1" r="0.4353" g="0.4353" b="0.4353" a="1.0" />
		<voxel x="5" y="5" z="1" r="0.3804" g="0.3804" b="0.3804" a="1.0" />
		<voxel x="6" y="5" z="1" r="0.3255" g="0.3255" b="0.3255" a="1.0" />
		<voxel x="7" y="5" z="1" r="0.2667" g="0.2667" b="0.2667" a="1.0" />
		<voxel x="8" y="5" z="1" r="0.2118" g="0.2118" b="0.2118" a="1.0" />
		<voxel x="-18" y="5" z="0" r="0.2118" g="0.2118" b="0.2118" a="1.0" />
		<voxel x="-17" y="5" z="0" r="0.3569" g="0.3569" b="0.3569" a="1.0" />
		<voxel x="-16" y="5" z="0" r="0.2118" g="0.2118" b="0.2118" a="1.0" />
		<voxel x="-15" y="5" z="0" r="0.2118" g="0.2118" b="0.2118" a="1.0" />
		<voxel x="-14" y="5" z="0" r="0.2118" g="0.2118" b="0.2118" a="1.0" />
		<voxel x="-13" y="5" z="0" r="0.2118" g="0.2118" b="0.2118" a="1.0" />
		<voxel x="-12" y="5" z="0" r="0.2118" g="0.2118" b="0.2118" a="1.0" />
		<voxel x="-11" y="5" z="0" r="0.2118" g="0.2118" b="0.2118" a="1.0" />
		<voxel x="-10" y="5" z="0" r="0.3059" g="0.3059" b="0.3059" a="1.0" />
		<voxel x="-9" y="5" z="0" r="0.3059" g="0.3059" b="0.3059" a="1.0" />
		<voxel x="-8" y="5" z="0" r="0.6039" g="0.6039" b="0.6039" a="1.0" />
		<voxel x="-7" y="5" z="0" r="0.6039" g="0.6039" b="0.6039" a="1.0" />
		<voxel x="-6" y="5" z="0" r="0.6039" g="0.6039" b="0.6039" a="1.0" />
		<voxel x="-5" y="5" z="0" r="0.6039" g="0.6039" b="0.6039" a="1.0" />
		<voxel x="-4" y="5" z="0" r="0.6039" g="0.6039" b="0.6039" a="1.0" />
		<voxel x="-3" y="5" z="0" r="0.6039" g="0.6039" b="0.6039" a="1.0" />
		<voxel x="-2" y="5" z="0" r="0.4902" g="0.4902" b="0.4902" a="1.0" />
		<voxel x="-1" y="5" z="0" r="0.4902" g="0.4902" b="0.4902" a="1.0" />
		<voxel x="0" y="5" z="0" r="0.549" g="0.549" b="0.549" a="1.0" />
		<voxel x="1" y="5" z="0" r="0.6039" g="0.6039" b="0.6039" a="1.0" />
		<voxel x="2" y="5" z="0" r="0.549" g="0.549" b="0.549" a="1.0" />
		<voxel x="3" y="5" z="0" r="0.4902" g="0.4902" b="0.4902" a="1.0" />
		<voxel x="4" y="5" z="0" r="0.4353" g="0.4353" b="0.4353" a="1.0" />
		<voxel x="5" y="5" z="0" r="0.3804" g="0.3804" b="0.3804" a="1.0" />
		<voxel x="6" y="5" z="0" r="0.3255" g="0.3255" b="0.3255" a="1.0" />
		<voxel x="7" y="5" z="0" r="0.2667" g="0.2667" b="0.2667" a="1.0" />
		<voxel x="8" y="5" z="0" r="0.2118" g="0.2118" b="0.2118" a="1.0" />
		<voxel x="-18" y="5" z="-1" r="0.4902" g="0.4902" b="0.4902" a="1.0" />
		<voxel x="-17" y="5" z="-1" r="0.6039" g="0.6039" b="0.6039" a="1.0" />
		<voxel x="-16" y="5" z="-1" r="0.6039" g="0.6039" b="0.6039" a="1.0" />
		<voxel x="-15" y="5" z="-1" r="0.6039" g="0.6039" b="0.6039" a="1.0" />
		<voxel x="-14" y="5" z="-1" r="0.6039" g="0.6039" b="0.6039" a="1.0" />
		<voxel x="-13" y="5" z="-1" r="0.549" g="0.549" b="0.549" a="1.0" />
		<voxel x="-12" y="5" z="-1" r="0.549" g="0.549" b="0.549" a="1.0" />
		<voxel x="-11" y="5" z="-1" r="0.4353" g="0.4353" b="0.4353" a="1.0" />
		<voxel x="-10" y="5" z="-1" r="0.6039" g="0.6039" b="0.6039" a="1.0" />
		<voxel x="-9" y="5" z="-1" r="0.6039" g="0.6039" b="0.6039" a="1.0" />
		<voxel x="-8" y="5" z="-1" r="0.549" g="0.549" b="0.549" a="1.0" />
		<voxel x="-7" y="5" z="-1" r="0.6039" g="0.6039" b="0.6039" a="1.0" />
		<voxel x="-6" y="5" z="-1" r="0.4353" g="0.4353" b="0.4353" a="1.0" />
		<voxel x="-5" y="5" z="-1" r="0.6039" g="0.6039" b="0.6039" a="1.0" />
		<voxel x="-4" y="5" z="-1" r="0.6039" g="0.6039" b="0.6039" a="1.0" />
		<voxel x="-3" y="5" z="-1" r="0.6039" g="0.6039" b="0.6039" a="1.0" />
		<voxel x="-2" y="5" z="-1" r="0.4902" g="0.4902" b="0.4902" a="1.0" />
		<voxel x="-1" y="5" z="-1" r="0.4902" g="0.4902" b="0.4902" a="1.0" />
		<voxel x="0" y="5" z="-1" r="0.549" g="0.549" b="0.549" a="1.0" />
		<voxel x="1" y="5" z="-1" r="0.6039" g="0.6039" b="0.6039" a="1.0" />
		<voxel x="2" y="5" z="-1" r="0.549" g="0.549" b="0.549" a="1.0" />
		<voxel x="3" y="5" z="-1" r="0.4902" g="0.4902" b="0.4902" a="1.0" />
		<voxel x="4" y="5" z="-1" r="0.4353" g="0.4353" b="0.4353" a="1.0" />
		<voxel x="5" y="5" z="-1" r="0.3804" g="0.3804" b="0.3804" a="1.0" />
		<voxel x="6" y="5" z="-1" r="0.3255" g="0.3255" b="0.3255" a="1.0" />
		<voxel x="7" y="5" z="-1" r="0.2667" g="0.2667" b="0.2667" a="1.0" />
		<voxel x="8" y="5" z="-1" r="0.2118" g="0.2118" b="0.2118" a="1.0" />
		<voxel x="-18" y="6" z="1" r="0.4902" g="0.4902" b="0.4902" a="1.0" />
		<voxel x="-17" y="6" z="1" r="0.3569" g="0.3569" b="0.3569" a="1.0" />
		<voxel x="-16" y="6" z="1" r="0.3569" g="0.3569" b="0.3569" a="1.0" />
		<voxel x="-15" y="6" z="1" r="1.0" g="0.7608" b="0.0" a="1.0" />
		<voxel x="-14" y="6" z="1" r="1.0" g="0.7608" b="0.0" a="1.0" />
		<voxel x="-13" y="6" z="1" r="1.0" g="0.7608" b="0.0" a="1.0" />
		<voxel x="-12" y="6" z="1" r="0.3255" g="0.3255" b="0.3255" a="1.0" />
		<voxel x="-11" y="6" z="1" r="0.4902" g="0.4902" b="0.4902" a="1.0" />
		<voxel x="-10" y="6" z="1" r="0.3373" g="0.3373" b="0.3373" a="1.0" />
		<voxel x="-9" y="6" z="1" r="0.3373" g="0.3373" b="0.3373" a="1.0" />
		<voxel x="-8" y="6" z="1" r="0.6039" g="0.6039" b="0.6039" a="1.0" />
		<voxel x="-7" y="6" z="1" r="0.549" g="0.549" b="0.549" a="1.0" />
		<voxel x="-6" y="6" z="1" r="0.6039" g="0.6039" b="0.6039" a="1.0" />
		<voxel x="-5" y="6" z="1" r="0.549" g="0.549" b="0.549" a="1.0" />
		<voxel x="-4" y="6" z="1" r="0.6039" g="0.6039" b="0.6039" a="1.0" />
		<voxel x="-3" y="6" z="1" r="0.6039" g="0.6039" b="0.6039" a="1.0" />
		<voxel x="-2" y="6" z="1" r="0.4902" g="0.4902" b="0.4902" a="1.0" />
		<voxel x="-1" y="6" z="1" r="0.4902" g="0.4902" b="0.4902" a="1.0" />
		<voxel x="0" y="6" z="1" r="0.549" g="0.549" b="0.549" a="1.0" />
		<voxel x="6" y="6" z="1" r="0.3255" g="0.3255" b="0.3255" a="1.0" />
		<voxel x="7" y="6" z="1" r="0.2667" g="0.2667" b="0.2667" a="1.0" />
		<voxel x="-20" y="6" z="0" r="0.7059" g="0.7059" b="0.7059" a="1.0" />
		<voxel x="-19" y="6" z="0" r="0.3569" g="0.3569" b="0.3569" a="1.0" />
		<voxel x="-18" y="6" z="0" r="0.3569" g="0.3569" b="0.3569" a="1.0" />
		<voxel x="-17" y="6" z="0" r="0.3569" g="0.3569" b="0.3569" a="1.0" />
		<voxel x="-16" y="6" z="0" r="0.3569" g="0.3569" b="0.3569" a="1.0" />
		<voxel x="-15" y="6" z="0" r="0.3569" g="0.3569" b="0.3569" a="1.0" />
		<voxel x="-14" y="6" z="0" r="1.0" g="0.7608" b="0.0" a="1.0" />
		<voxel x="-13" y="6" z="0" r="0.3569" g="0.3569" b="0.3569" a="1.0" />
		<voxel x="-12" y="6" z="0" r="0.3569" g="0.3569" b="0.3569" a="1.0" />
		<voxel x="-11" y="6" z="0" r="0.3569" g="0.3569" b="0.3569" a="1.0" />
		<voxel x="-10" y="6" z="0" r="0.3059" g="0.3059" b="0.3059" a="1.0" />
		<voxel x="-9" y="6" z="0" r="0.3059" g="0.3059" b="0.3059" a="1.0" />
		<voxel x="-8" y="6" z="0" r="0.6039" g="0.6039" b="0.6039" a="1.0" />
		<voxel x="-7" y="6" z="0" r="0.6039" g="0.6039" b="0.6039" a="1.0" />
		<voxel x="-6" y="6" z="0" r="0.6039" g="0.6039" b="0.6039" a="1.0" />
		<voxel x="-5" y="6" z="0" r="0.6039" g="0.6039" b="0.6039" a="1.0" />
		<voxel x="-4" y="6" z="0" r="0.6039" g="0.6039" b="0.6039" a="1.0" />
		<voxel x="-3" y="6" z="0" r="0.6039" g="0.6039" b="0.6039" a="1.0" />
		<voxel x="-2" y="6" z="0" r="0.4902" g="0.4902" b="0.4902" a="1.0" />
		<voxel x="-1" y="6" z="0" r="0.4902" g="0.4902" b="0.4902" a="1.0" />
		<voxel x="0" y="6" z="0" r="0.549" g="0.549" b="0.549" a="1.0" />
		<voxel x="1" y="6" z="0" r="0.6039" g="0.6039" b="0.6039" a="1.0" />
		<voxel x="5" y="6" z="0" r="0.3804" g="0.3804" b="0.3804" a="1.0" />
		<voxel x="6" y="6" z="0" r="0.3255" g="0.3255" b="0.3255" a="1.0" />
		<voxel x="7" y="6" z="0" r="0.2667" g="0.2667" b="0.2667" a="1.0" />
		<voxel x="8" y="6" z="0" r="0.2118" g="0.2118" b="0.2118" a="1.0" />
		<voxel x="-18" y="6" z="-1" r="0.4902" g="0.4902" b="0.4902" a="1.0" />
		<voxel x="-17" y="6" z="-1" r="0.3569" g="0.3569" b="0.3569" a="1.0" />
		<voxel x="-16" y="6" z="-1" r="0.3569" g="0.3569" b="0.3569" a="1.0" />
		<voxel x="-15" y="6" z="-1" r="1.0" g="0.7608" b="0.0" a="1.0" />
		<voxel x="-14" y="6" z="-1" r="1.0" g="0.7608" b="0.0" a="1.0" />
		<voxel x="-13" y="6" z="-1" r="1.0" g="0.7608" b="0.0" a="1.0" />
		<voxel x="-12" y="6" z="-1" r="0.3255" g="0.3255" b="0.3255" a="1.0" />
		<voxel x="-11" y="6" z="-1" r="0.3451" g="0.3451" b="0.3451" a="1.0" />
		<voxel x="-10" y="6" z="-1" r="0.3373" g="0.3373" b="0.3373" a="1.0" />
		<voxel x="-9" y="6" z="-1" r="0.3373" g="0.3373" b="0.3373" a="1.0" />
		<voxel x="-8" y="6" z="-1" r="0.6039" g="0.6039" b="0.6039" a="1.0" />
		<voxel x="-7" y="6" z="-1" r="0.549" g="0.549" b="0.549" a="1.0" />
		<voxel x="-6" y="6" z="-1" r="0.6039" g="0.6039" b="0.6039" a="1.0" />
		<voxel x="-5" y="6" z="-1" r="0.549" g="0.549" b="0.549" a="1.0" />
		<voxel x="-4" y="6" z="-1" r="0.6039" g="0.6039" b="0.6039" a="1.0" />
		<voxel x="-3" y="6" z="-1" r="0.6039" g="0.6039" b="0.6039" a="1.0" />
		<voxel x="-2" y="6" z="-1" r="0.4902" g="0.4902" b="0.4902" a="1.0" />
		<voxel x="-1" y="6" z="-1" r="0.4902" g="0.4902" b="0.4902" a="1.0" />
		<voxel x="0" y="6" z="-1" r="0.549" g="0.549" b="0.549" a="1.0" />
		<voxel x="6" y="6" z="-1" r="0.3255" g="0.3255" b="0.3255" a="1.0" />
		<voxel x="7" y="6" z="-1" r="0.2667" g="0.2667" b="0.2667" a="1.0" />
		<voxel x="-17" y="7" z="1" r="0.3569" g="0.3569" b="0.3569" a="1.0" />
		<voxel x="-16" y="7" z="1" r="0.3569" g="0.3569" b="0.3569" a="1.0" />
		<voxel x="-15" y="7" z="1" r="0.3373" g="0.3373" b="0.3373" a="1.0" />
		<voxel x="-14" y="7" z="1" r="1.0" g="0.7608" b="0.0" a="1.0" />
		<voxel x="-13" y="7" z="1" r="0.3255" g="0.3255" b="0.3255" a="1.0" />
		<voxel x="-12" y="7" z="1" r="0.3255" g="0.3255" b="0.3255" a="1.0" />
		<voxel x="-11" y="7" z="1" r="0.3569" g="0.3569" b="0.3569" a="1.0" />
		<voxel x="-6" y="7" z="1" r="0.5451" g="0.5451" b="0.5451" a="1.0" />
		<voxel x="-5" y="7" z="1" r="0.6039" g="0.6039" b="0.6039" a="1.0" />
		<voxel x="-4" y="7" z="1" r="0.5451" g="0.5451" b="0.5451" a="1.0" />
		<voxel x="-18" y="7" z="0" r="0.3569" g="0.3569" b="0.3569" a="1.0" />
		<voxel x="-17" y="7" z="0" r="0.3569" g="0.3569" b="0.3569" a="1.0" />
		<voxel x="-16" y="7" z="0" r="0.3569" g="0.3569" b="0.3569" a="1.0" />
		<voxel x="-15" y="7" z="0" r="0.3569" g="0.3569" b="0.3569" a="1.0" />
		<voxel x="-14" y="7" z="0" r="1.0" g="0.7608" b="0.0" a="1.0" />
		<voxel x="-13" y="7" z="0" r="0.3569" g="0.3569" b="0.3569" a="1.0" />
		<voxel x="-12" y="7" z="0" r="0.3569" g="0.3569" b="0.3569" a="1.0" />
		<voxel x="-11" y="7" z="0" r="0.3569" g="0.3569" b="0.3569" a="1.0" />
		<voxel x="-10" y="7" z="0" r="0.3059" g="0.3059" b="0.3059" a="1.0" />
		<voxel x="-6" y="7" z="0" r="0.5451" g="0.5451" b="0.5451" a="1.0" />
		<voxel x="-5" y="7" z="0" r="0.5765" g="0.5765" b="0.5765" a="1.0" />
		<voxel x="-4" y="7" z="0" r="0.5451" g="0.5451" b="0.5451" a="1.0" />
		<voxel x="-3" y="7" z="0" r="0.5765" g="0.5765" b="0.5765" a="1.0" />
		<voxel x="-17" y="7" z="-1" r="0.3569" g="0.3569" b="0.3569" a="1.0" />
		<voxel x="-16" y="7" z="-1" r="0.3569" g="0.3569" b="0.3569" a="1.0" />
		<voxel x="-15" y="7" z="-1" r="0.3373" g="0.3373" b="0.3373" a="1.0" />
		<voxel x="-14" y="7" z="-1" r="1.0" g="0.7608" b="0.0" a="1.0" />
		<voxel x="-13" y="7" z="-1" r="0.3255" g="0.3255" b="0.3255" a="1.0" />
		<voxel x="-12" y="7" z="-1" r="0.3255" g="0.3255" b="0.3255" a="1.0" />
		<voxel x="-11" y="7" z="-1" r="0.3451" g="0.3451" b="0.3451" a="1.0" />
		<voxel x="-6" y="7" z="-1" r="0.5451" g="0.5451" b="0.5451" a="1.0" />
		<voxel x="-5" y="7" z="-1" r="0.6039" g="0.6039" b="0.6039" a="1.0" />
		<voxel x="-4" y="7" z="-1" r="0.5451" g="0.5451" b="0.5451" a="1.0" />
		<voxel x="-16" y="8" z="0" r="0.3569" g="0.3569" b="0.3569" a="1.0" />
		<voxel x="-15" y="8" z="0" r="0.3569" g="0.3569" b="0.3569" a="1.0" />
		<voxel x="-14" y="8" z="0" r="1.0" g="0.7608" b="0.0" a="1.0" />
		<voxel x="-13" y="8" z="0" r="0.3569" g="0.3569" b="0.3569" a="1.0" />
		<voxel x="-12" y="8" z="0" r="0.3569" g="0.3569" b="0.3569" a="1.0" />
		<voxel x="-11" y="8" z="0" r="0.3569" g="0.3569" b="0.3569" a="1.0" />
	</voxels>
	<skeleton />
	<skeletonVoxelBindings />
</model>