<?xml version="1.0" encoding="utf-8"?>
<vehicles>
	<!--63式火箭炮-->
	<vehicle file="63type_107mm_rocket_launcher.vehicle" />

	<!-- 坦克 -->
	<vehicle file="ex_sturmtiger_tank.vehicle" /><!-- 突击虎 -->
	<vehicle file="ex_apocalypse_tank.vehicle" /><!-- 天启 -->
	<vehicle file="ex_guntruck_plus.vehicle" /><!-- 灵位卡车 -->
	<vehicle file="ba_crusader.vehicle" /><!-- 十字军 -->
	<vehicle file="ex_m18.vehicle" /><!-- M18 地狱猫 -->
	<vehicle file="ba_torumaru_tiger.vehicle" /><!--虎丸 [伊吕波] 重型坦克-->
	<vehicle file="himars.vehicle" /><!--海马斯火箭发射平台-->
	<vehicle file="m61a5.vehicle" /><!--M61A5 双炮座坦克-->
	<vehicle file="borsig.vehicle" /><!-- 雪貂-->
	<vehicle file="uragan.vehicle" /><!-- uragan 火箭车-->
	<vehicle file="zbd09.vehicle" /><!-- ZBD09-->
	<vehicle file="ex_power_chair.vehicle" /><!--力量の椅-->
	<vehicle file="lav6.vehicle" /><!--lav6-->
	<vehicle file="kirov.vehicle" /><!--基洛夫-->
	<vehicle file="panther_a.vehicle" /><!--豹式坦克A型-->
	<vehicle file="sdkfz184.vehicle" /><!--大象-->
	<vehicle file="ex_warthog.vehicle" /><!--疣猪号机枪吉普-->
	<vehicle file="ex_nova.vehicle" /><!--NOVA-->
	<vehicle file="ex_yaluji.vehicle" /><!--压路机-->
	<vehicle file="ex_unsc_scion.vehicle" /><!--天蝎-->
	<vehicle file="miyu_home.vehicle" /><!--美游垃圾桶-->
	

	<!-- 原版 -->
	<vehicle file="radar_tower.vehicle" />
	<vehicle file="radio_jammer.vehicle" />
	<vehicle file="radio_jammer2.vehicle" />
	<vehicle file="icecream.vehicle" />
	<!-- <vehicle file="darkcat.vehicle" /> -->
	<vehicle file="mobile_armory.vehicle" />
	<vehicle file="noxe.vehicle" />
	<vehicle file="repair_crane.vehicle" />
	<vehicle file="wiesel_tow.vehicle" />

	<!-- 特殊 -->
	<vehicle file="ex_piano.vehicle" /><!--主题钢琴-->
	<vehicle file="ex_gramophone.vehicle" />	<!--唱片-->
	<vehicle file="stash_box.vehicle" />	<!--脚本仓库-->
	<vehicle file="work_table_box.vehicle" />   
	<vehicle file="hide_box.vehicle" />   <!--烟雾弹墙-->

	<!-- 飞机 -->
	<vehicle file="mi_24.vehicle" />	<!--米 24 直升机-->
	<vehicle file="bell_360.vehicle" />	<!--贝尔360 直升机-->
	<vehicle file="mh_60s.vehicle" />	<!--贝尔360 直升机-->

	<!-- 部署物 -->
	<vehicle file="ex_pak40.vehicle" />	<!--德国反坦克炮-->
	<vehicle file="ex_zis3.vehicle" />	<!--苏联反坦克炮-->
	<!-- 替换黄蜂陶氏 -->
	<vehicle file="ex_edf_turrent_single.vehicle" />
	<vehicle file="ex_edf_turrent_double.vehicle" />
	<vehicle file="ex_edf_turrent_single_ex.vehicle" />
	<vehicle file="ex_edf_turrent_double_ex.vehicle" />
	<!-- 替换迫击炮 -->
	<vehicle file="ex_edf_mortar.vehicle" />
	<vehicle file="ex_edf_mortar_ex.vehicle" />
	<!-- 替换机枪 -->
	<vehicle file="ex_edf_turrent_minigun.vehicle" />
	<vehicle file="ex_edf_turrent_minigun_ex.vehicle" />
	
	<vehicle file="ex_vanilla_replace.vehicle" />
	
	<!-- 赛车 -->
	<vehicle file="racing_car1.vehicle" />	
	<vehicle file="racing_car1.vehicle" />	
  	<vehicle file="racing_car2.vehicle" />
	<vehicle file="racing_car3.vehicle" />
	<vehicle file="racing_car4.vehicle" />
	<vehicle file="racing_car5.vehicle" />
	<vehicle file="racing_car6.vehicle" />
	<vehicle file="racing_car7.vehicle" />
	<vehicle file="racing_car8.vehicle" /> 
	<vehicle file="straw_block.vehicle" />   

	<vehicle file="racing.vehicle" />   

	<!-- 活动载具 -->
	<vehicle file="act_hongbao.vehicle" />   
	<vehicle file="hd_models.vehicle" />   
	
</vehicles>
